McQueen/__init__.py
McQueen/check_domain_age.py
McQueen/check_domain_registrant.py
McQueen/colors.py
McQueen/crawl_website_pages.py
McQueen/detect_firewall.py
McQueen/error_handler.py
McQueen/main.py
McQueen/mcqueen.py
McQueen/scan_subdomain.py
McQueen/track_ip_location.py
McQueen/track_website_information.py
McQueen/validations.py
McQueen-0.5.0.dist-info/LICENSE
McQueen-0.5.0.dist-info/METADATA
McQueen-0.5.0.dist-info/WHEEL
McQueen-0.5.0.dist-info/entry_points.txt
McQueen-0.5.0.dist-info/top_level.txt
McQueen-0.5.0.dist-info/RECORD
